{
  "trial_plot": {
    "title": "Sensor timestamp Vs Pupil x position",
    "x_label": "sensor timestamp",
    "y_label": "pupil position",
    "x_data_column_name": "t",
    "y_data_column_name": "x",
    "x_axis_limit": [0, 7],
    "y_axis_limit": [0.4, 0.5],
    "mean_offset": 0.05,
    "axis_adjustment_types": {"1":"manual", "2":"min_max", "3":"mean_offset"},
    "axis_adjustment_type_number": 3,
    "graph_line_color": "black",
    "graph_line_thickness": 1,
    "image_scale": 5,
    "signal_csv_folder_name": "result",
    "signal_csv_name": "signal.csv",
    "sp_column_name": "is_sp",
    "qp_column_name": "is_qp",
    "sp_line_color": "green",
    "sp_line_thickness": 2,
    "qp_line_color": "red",
    "qp_line_thickness": 2,
    "output_image_name": "trial_sensor_ts_vs_x_nom.png"
  },
  "summary_plot": {
    "title_font_size": 22,
    "x_label": "sensor timestamp",
    "y_label": "pupil position",
    "label_font_size": 20,
    "x_data_column_name": "t",
    "y_data_column_name": "x",
    "x_axis_limit": [0, 7],
    "y_axis_limit": [0.4, 0.5],
    "mean_offset": 0.05,
    "axis_adjustment_types": {"1":"manual", "2":"min_max", "3":"min_max_mean", "4":"mean_offset"},
    "axis_adjustment_type_number": 4,
    "graph_line_color": "black",
    "graph_line_thickness": 1,
    "max_graph_in_a_row": "none",
    "image_scale": 5,
    "extra_width_scale_for_sweep": 4,
    "signal_csv_folder_name": "result",
    "signal_csv_name": "signal.csv",
    "sp_column_name": "is_sp",
    "qp_column_name": "is_qp",
    "sp_line_color": "green",
    "sp_line_thickness": 2,
    "qp_line_color": "red",
    "qp_line_thickness": 2,
    "summary_csv_name": "okn_detector_summary.csv",
    "output_image_name": "okn_detector_summary.png"
  },
  "progress_plot": {
    "x_label": "Trial",
    "y_label": "LogMAR",
    "x_data_column_name": "trial_id",
    "y_data_column_name": "logmar_level",
    "okn_matlab_column_name": "okn_matlab",
    "phase_column_name": "phase",
    "final_logmar_column_name": "final_logmar",
    "graph_line_color": "black",
    "graph_line_thickness": 1,
    "graph_line_style": "dashed",
    "summary_csv_name": "okn_detector_summary.csv",
    "trial_summary_csv_name": "trial_data.csv",
    "output_image_name": "va_progress.png",
    "marker_type_equivalent": {
      "circle": "o",
      "triangle": "^",
      "square": "s",
      "star": "*",
      "diamond": "D",
      "thin_diamond": "d",
      "plus": "P"
    },
    "marker_type": "square",
    "marker_size": 10,
    "okn_marker_color": "black",
    "okn_marker_edge_color": "black",
    "okn_legend_label": "OKN",
    "non_okn_marker_color": "white",
    "non_okn_marker_edge_color": "black",
    "non_okn_legend_label": "NO OKN",
    "best_va_line": true,
    "best_va_line_color": "black",
    "best_va_line_thickness": 1,
    "best_va_line_style": "dotted",
    "best_va_line_legend_label": "Best VA",
    "final_va_line": true,
    "final_va_line_color": "black",
    "final_va_line_thickness": 1,
    "final_va_line_style": "dashed",
    "final_va_line_legend_label": "Final VA",
    "legend_background_color": "white",
    "legend_edge_color": "black",
    "legend_location": "upper right",
    "legend_font_size": "small",
    "legend_icon_size": 8,
    "line_style_equivalent": {
      "solid": "-",
      "dashed": "--",
      "dash-dot": "-.",
      "dotted": ":"
    }
  },
  "tidy_plot": {
    "x_label": "Trial",
    "x_label_x_position": 0.5,
    "x_label_y_position": 0.08,
    "x_label_alignment": "center",
    "x_label_rotation": 0,
    "x_label_weight": "bold",
    "x_label_font_size": 40,
    "y_label": "VA LogMAR",
    "y_label_x_position": 0.06,
    "y_label_y_position": 0.5,
    "y_label_alignment": "center",
    "y_label_rotation": 90,
    "y_label_weight": "bold",
    "y_label_font_size": 40,
    "main_boundary_position": [0.12, 0.11],
    "main_boundary_width": 0.80,
    "main_boundary_height": 0.78,
    "main_boundary_color": "black",
    "main_boundary_line_thickness": 2,
    "x_data_column_name": "t",
    "y_data_column_name": "x",
    "x_axis_limit": [0, 7],
    "y_axis_limit": [0.4, 0.5],
    "mean_offset": 0.1,
    "axis_adjustment_types": {"1":"manual", "2":"min_max", "3":"min_max_mean", "4":"mean_offset"},
    "axis_adjustment_type_number": 4,
    "axis_y_label_rotation": 0,
    "axis_y_label_weight": "bold",
    "axis_y_label_font_size": 25,
    "axis_y_label_pad": 40,
    "axis_right_top_left_bottom_borders": [false, false, false, false],
    "subplots_space_adjustment": true,
    "subplots_width_space": 0.2,
    "subplots_height_space": -0.1,
    "mid_line": true,
    "mid_line_level": 0,
    "mid_line_color": "black",
    "mid_line_style": "dotted",
    "mid_line_thickness": 1,
    "graph_line_color": "black",
    "graph_line_thickness": 1,
    "image_scale": 5,
    "signal_csv_folder_name": "result",
    "signal_csv_name": "signal.csv",
    "sp_column_name": "is_sp",
    "qp_column_name": "is_qp",
    "sp_line_color": "green",
    "sp_line_thickness": 2,
    "qp_line_color": "red",
    "qp_line_thickness": 2,
    "time_notation": "7 sec",
    "time_notation_text_position": [0.815, 0.918],
    "time_notation_text_weight": "bold",
    "time_notation_text_font_size": 25,
    "time_line_x_position_start_end": [0.766, 0.9],
    "time_line_y_position_start_end": [0.94, 0.94],
    "time_line_style": "solid",
    "time_line_color": "black",
    "time_line_thickness": 2,
    "time_boundary_position": [0.748, 0.91],
    "time_boundary_width": 0.172,
    "time_boundary_height": 0.05,
    "time_boundary_color": "black",
    "time_boundary_line_thickness": 2,
    "summary_csv_name": "okn_detector_summary.csv",
    "output_image_name": "okn_detector_summary_tidy.png"
  }
}